dj_graphene/__init__.py
dj_graphene/apps.py
dj_graphene/mixins.py
dj_graphene/permissions.py
dj_graphene/tests.py
dj_graphene/types.py
dj_graphene-0.0.2.dist-info/LICENSE.TXT
dj_graphene-0.0.2.dist-info/METADATA
dj_graphene-0.0.2.dist-info/WHEEL
dj_graphene-0.0.2.dist-info/top_level.txt
dj_graphene-0.0.2.dist-info/RECORD
