Metadata-Version: 2.1
Name: dj-graphene
Version: 0.0.2
Summary: A graphene-django wrapper to do more writing less 💃🕺
Home-page: https://github.com/YasielCabrera/dj-graphene
Author: Yasiel Cabrera
Author-email: yasiel9506@gmail.com
License: MIT
Keywords: GRAPHENE,GRAPHENE-DJANGO,GRAPHQL,DJANGO,MODELS,API,PERMISSIONS
Platform: UNKNOWN
Classifier: Development Status :: 3 - Alpha
Classifier: Intended Audience :: Developers
Classifier: Topic :: Software Development :: Build Tools
Classifier: License :: OSI Approved :: MIT License
Classifier: Environment :: Web Environment
Classifier: Framework :: Django
Classifier: Programming Language :: Python :: 3
Classifier: Programming Language :: Python :: 3.6
Classifier: Programming Language :: Python :: 3.7
Classifier: Programming Language :: Python :: 3.8
Classifier: Programming Language :: Python :: 3.9
Requires-Dist: graphene
Requires-Dist: graphene-django
Requires-Dist: django
